<PAMDataset>
  <PAMRasterBand band="1">
    <Histograms>
      <HistItem>
        <HistMin>-0.498046875</HistMin>
        <HistMax>255.498046875</HistMax>
        <BucketCount>256</BucketCount>
        <IncludeOutOfRange>0</IncludeOutOfRange>
        <Approximate>1</Approximate>
        <HistCounts>39522|618|571|657|671|702|743|788|812|796|775|788|803|789|748|785|805|760|701|732|731|754|673|681|709|687|674|715|685|664|693|610|703|643|645|637|647|670|634|616|584|636|647|651|649|618|668|631|566|653|627|582|564|576|570|565|570|565|546|559|516|519|568|572|509|521|522|502|531|517|551|525|519|485|487|460|468|524|487|513|427|475|464|445|486|490|444|488|446|511|498|442|452|454|451|452|445|453|436|474|459|456|458|485|446|471|452|468|479|451|477|468|460|478|466|458|441|454|509|457|409|478|497|478|496|456|497|479|463|469|508|508|541|569|548|494|513|512|542|541|548|577|626|598|618|648|673|766|724|714|764|813|817|864|894|958|952|1015|1092|1174|1243|1320|1382|1518|1629|1753|1881|2042|2264|2444|2613|2759|3053|3491|4125|4091|4283|4866|5426|6167|7268|8977|12625|21931|52250|9739|6012|4116|3240|3047|2878|3019|2982|3187|3445|3638|3771|4031|4571|4702|5198|5562|5855|6425|7123|7690|8309|9076|9919|11098|12291|14187|16373|176440|25182|191023|170491|481926|75609|219961|13484|6074|3494|2472|1832|1645|1550|1478|1447|1473|1418|1507|1548|1625|1652|1677|1840|1969|2164|2312|2436|2636|2865|3045|3431|3661|4146|4417|5102|5811|6720|8144|10179|13525|24126|681851</HistCounts>
      </HistItem>
    </Histograms>
    <Metadata>
      <MDI key="STATISTICS_MAXIMUM">255</MDI>
      <MDI key="STATISTICS_MEAN">216.38878963436</MDI>
      <MDI key="STATISTICS_MINIMUM">0</MDI>
      <MDI key="STATISTICS_STDDEV">44.721897177871</MDI>
    </Metadata>
  </PAMRasterBand>
</PAMDataset>
